{"cameraMode":{"drawMode":0,"name":"Shaded","section":"Shading Mode"},"sceneLighting":true,"audioPlay":false,"sceneViewState":{"showFog":true,"showMaterialUpdate":false,"showSkybox":true,"showFlares":true,"showImageEffects":true,"showParticleSystems":true},"in2DMode":false,"pivot":{"x":-6.53696346282959,"y":-35.47187042236328,"z":42.208152770996097},"rotation":{"x":-0.061680469661951068,"y":0.054469309747219089,"z":-0.0033544101752340795,"w":-0.9966239333152771},"size":151.94520568847657,"orthographic":false}